[
	{
		"지역이름": "Idle",
		"값": "Idle",
		"CamZoom": "3(Default)",
		"": "",
		"": ""
	},
	{
		"지역이름": "Run",
		"값": "run_strafe_front",
		"CamZoom": 3,
		"": "",
		"": ""
	},
	{
		"지역이름": "Run_Front_L45",
		"값": "run_strafe_frontleft",
		"CamZoom": 3,
		"": "",
		"": ""
	},
	{
		"지역이름": "Run_Front_R45",
		"값": "run_strafe_frontright",
		"CamZoom": 3,
		"": "",
		"": ""
	},
	{
		"지역이름": "Run_Attack",
		"값": "Dash_Attack_ver_B",
		"CamZoom": "",
		"": "",
		"": ""
	},
	{
		"지역이름": "Guard",
		"값": "Revenge_Guard_Accept",
		"CamZoom": 3,
		"": "",
		"": ""
	},
	{
		"지역이름": "Guard_Attack",
		"값": "Skill_I",
		"CamZoom": "",
		"": "",
		"": ""
	},
	{
		"지역이름": "Dodge_Front",
		"값": "roll_front",
		"CamZoom": 3,
		"": "",
		"": ""
	},
	{
		"지역이름": "Dodge_Left",
		"값": "Roll_Left",
		"CamZoom": 3,
		"": "",
		"": ""
	},
	{
		"지역이름": "Dodge_Right",
		"값": "Roll_Right",
		"CamZoom": 3,
		"": "",
		"": ""
	},
	{
		"지역이름": "Dodge_Back",
		"값": "M_katana_Blade@Dodge_Back",
		"CamZoom": 3,
		"": "",
		"": ""
	},
	{
		"지역이름": "Dodge_Attack",
		"값": "M_katana_Blade@Skill_A",
		"CamZoom": "",
		"": "",
		"": ""
	},
	{
		"지역이름": "Damage",
		"값": "M_katana_Blade@Damage_Front_Big_ver_A",
		"CamZoom": "",
		"": "",
		"": ""
	},
	{
		"지역이름": "Nor_Attack01",
		"값": "Combo_01_1",
		"CamZoom": 3,
		"": "",
		"": ""
	},
	{
		"지역이름": "Nor_Attack02",
		"값": "Combo_01_2",
		"CamZoom": 3,
		"": "",
		"": ""
	},
	{
		"지역이름": "Nor_Attack03",
		"값": "Combo_01_3",
		"CamZoom": 3.5,
		"": "",
		"": ""
	},
	{
		"지역이름": "Nor_Attack04",
		"값": "Combo_02_3",
		"CamZoom": 3,
		"": "",
		"": ""
	},
	{
		"지역이름": "Nor_Attack05",
		"값": "Combo_03_3",
		"CamZoom": 3,
		"": "",
		"": ""
	},
	{
		"지역이름": "Nor_S Attack",
		"값": "Combo_03_4",
		"CamZoom": 3.8,
		"": "",
		"": ""
	},
	{
		"지역이름": "Nor_A_Attack06",
		"값": "M_katana_Blade@Attack_4Combo_3",
		"CamZoom": "",
		"": "",
		"": ""
	},
	{
		"지역이름": "Nor_A_Attack07",
		"값": "M_katana_Blade@Attack_4Combo_4",
		"CamZoom": "",
		"": "",
		"": ""
	},
	{
		"지역이름": "Com_Attack_Ready",
		"값": "Buff_01",
		"CamZoom": 3,
		"": "",
		"": ""
	},
	{
		"지역이름": "Com_Attack_01",
		"값": "Attack_3Combo_1",
		"CamZoom": "",
		"": "",
		"": ""
	},
	{
		"지역이름": "Com_Attack_02",
		"값": "Attack_3Combo_2",
		"CamZoom": "",
		"": "",
		"": ""
	},
	{
		"지역이름": "Com_Attack_03",
		"값": "Attack_3Combo_3",
		"CamZoom": "",
		"": "",
		"": ""
	},
	{
		"지역이름": "Com_Attack_04",
		"값": "Attack_4Combo_1B",
		"CamZoom": "",
		"": "",
		"": ""
	},
	{
		"지역이름": "Com_S Attack",
		"값": "M_Big_Sword@Skill_H",
		"CamZoom": "",
		"": "",
		"": ""
	},
	{
		"지역이름": "Com_A_Attack_04_1",
		"값": "Skill_J",
		"CamZoom": "",
		"": "",
		"": ""
	},
	{
		"지역이름": "Walk_Front",
		"값": "M_katana_Blade@Walk_ver_A_Front",
		"CamZoom": 3,
		"": "",
		"": ""
	},
	{
		"지역이름": "Walk_Front_L45",
		"값": "M_katana_Blade@Walk_ver_A_Front_L45",
		"CamZoom": 3,
		"": "",
		"": ""
	},
	{
		"지역이름": "Walk_Front_R45",
		"값": "M_katana_Blade@Walk_ver_A_Front_R45",
		"CamZoom": 3,
		"": "",
		"": ""
	}
]